{"urls":{"website":["http://www.btchd.org/"],"technical_doc":["http://www.btchd.org/BHD-Whitepaper-1.0_en.pdf"],"twitter":["https://twitter.com/btchdcommunity"],"reddit":[],"message_board":[],"announcement":[],"chat":["https://t.me/joinchat/KMU_Qwx_Zyg4s-vU28pvVw","https://discord.gg/pWde3gn"],"explorer":["https://btchd.org/explorer","https://bhd.tokenview.com/en"],"source_code":[]},"logo":"https://s2.coinmarketcap.com/static/img/coins/64x64/3966.png","id":3966,"name":"BitcoinHD","symbol":"BHD","slug":"bitcoinhd","description":"BitcoinHD (BHD) aims to create an energy efficient cryptocurrency and mining ecosystem. BTCHD’s goal is to create a currency that anyone can mine, manage, and use.","notice":null,"date_added":"2019-05-27T00:00:00.000Z","tags":null,"platform":null,"category":"coin"}