{"urls":{"website":["https://blockstack.org/"],"technical_doc":["https://blockstack.org/papers"],"twitter":["https://twitter.com/blockstack"],"reddit":[],"message_board":["https://blog.blockstack.org/","https://forum.blockstack.org/"],"announcement":[],"chat":["https://t.me/BlockstackChat","https://chat.blockstack.org/"],"explorer":["https://explorer.blockstack.org/"],"source_code":["https://github.com/blockstack"]},"logo":"https://s2.coinmarketcap.com/static/img/coins/64x64/4847.png","id":4847,"name":"Blockstack","symbol":"STX","slug":"blockstack","description":"Blockstack aims to build a new decentralized internet where users own their data and apps run locally. A browser portal would be all that is needed to get started.","notice":null,"date_added":"2019-10-28T00:00:00.000Z","tags":null,"platform":null,"category":"coin"}