{"urls":{"website":["https://token.coinhe.io/"],"technical_doc":["https://drive.google.com/file/d/1DtoWjDQfr_fT4IzfIMsjTqWEA9H_wwNq/view"],"twitter":["https://twitter.com/Coinheglobal"],"reddit":[],"message_board":["https://blog.coinhe.io/"],"announcement":["https://bitcointalk.org/index.php?topic=4996801.0"],"chat":["https://t.me/coinheio"],"explorer":["https://etherscan.io/token/0x3277dd536471a3cBEB0c9486aCad494C95A31E73","https://ethplorer.io/address/0x3277dd536471a3cBEB0c9486aCad494C95A31E73"],"source_code":[]},"logo":"https://s2.coinmarketcap.com/static/img/coins/64x64/4701.png","id":4701,"name":"CoinHe Token","symbol":"CHT","slug":"coinhe-token","description":"CHT (or CoinHe Token) is the ERC20-based token issued by CoinHe.io. CHT will not be sold by CoinHe but freely distributed to the community by airdrops and bounty campaigns. CoinHe will automatically distribute its revenue to CHT holders periodically. CHT holders will have certain rights towards any decision of the community.","notice":null,"date_added":"2019-10-19T00:00:00.000Z","tags":null,"platform":{"id":1027,"name":"Ethereum","symbol":"ETH","slug":"ethereum","token_address":"0x3277dd536471a3cBEB0c9486aCad494C95A31E73"},"category":"token"}