{"urls":{"website":["https://crowdwiz.io/"],"technical_doc":["https://crowdwiz.io/docs/whitepaper-en-1507561917.pdf"],"twitter":["https://twitter.com/Crowdwiz"],"reddit":["https://reddit.com/r/Crowdwiz_io"],"message_board":["https://medium.com/@crowdwiz.io","https://steemit.com/@crowdwiz"],"announcement":["https://bitcointalk.org/index.php?topic=4751634.0"],"chat":["https://t.me/crowdwiz"],"explorer":["https://etherscan.io/token/0x2f9b6779c37df5707249eeb3734bbfc94763fbe2","https://ethplorer.io/address/0x2f9b6779c37df5707249eeb3734bbfc94763fbe2"],"source_code":["https://github.com/CrowdWiz-io"]},"logo":"https://s2.coinmarketcap.com/static/img/coins/64x64/3331.png","id":3331,"name":"CrowdWiz","symbol":"WIZ","slug":"crowdwiz","description":"CrowdWiz (WIZ) is a cryptocurrency token and operates on the Ethereum platform. CrowdWiz has a current supply of 5,639,000 with 4,305,850.816 in circulation. The last known price of CrowdWiz is $0.003625 USD and is down -12.33% over the last 24 hours. It is currently trading on 5 active market(s) with $603.96 traded over the last 24 hours. More information can be found at https://crowdwiz.io/.","notice":null,"date_added":"2018-11-14T00:00:00.000Z","tags":null,"platform":{"id":1027,"name":"Ethereum","symbol":"ETH","slug":"ethereum","token_address":"0x2f9b6779c37df5707249eeb3734bbfc94763fbe2"},"category":"token"}