{"urls":{"website":["https://coin.digiwage.org"],"technical_doc":[],"twitter":["https://twitter.com/digiwage"],"reddit":["https://reddit.com/r/Digiwage"],"message_board":[],"announcement":[],"chat":["https://discord.gg/822ezXx"],"explorer":["https://explorer.digiwage.org/"],"source_code":["https://github.com/digiwage/digiwage"]},"logo":"https://s2.coinmarketcap.com/static/img/coins/64x64/3416.png","id":3416,"name":"Digiwage","symbol":"WAGE","slug":"digiwage","description":"Digiwage (WAGE) is a cryptocurrency. Users are able to generate WAGE through the process of mining. Digiwage has a current supply of 55,062,328.925 with 47,062,307.925 in circulation. The last known price of Digiwage is $0.000173 USD and is down -8.69% over the last 24 hours. It is currently trading on 1 active market(s) with $23.70 traded over the last 24 hours. More information can be found at https://coin.digiwage.org.","notice":null,"date_added":"2018-10-09T00:00:00.000Z","tags":["mineable"],"platform":null,"category":"coin"}