{"urls":{"website":["https://www.grnpower.io/"],"technical_doc":["https://www.grnpower.io/assets/file/GreenPower-White-Paper-1.1.pdf"],"twitter":["https://twitter.com/greenpower_grn"],"reddit":[],"message_board":[],"announcement":["https://bitcointalk.org/index.php?topic=5174117"],"chat":["https://t.me/joinchat/AAAAAFGvALq43sCHapvQYA"],"explorer":["https://grnexplorer.io/"],"source_code":["https://github.com/green-powerchain-ltd"]},"logo":"https://s2.coinmarketcap.com/static/img/coins/64x64/2746.png","id":2746,"name":"GreenPower","symbol":"GRN","slug":"greenpower","description":"GREENPOWER has been designed to serve as a global rewards currency. GREENPOWER was developed on Graphene and claims to feature a highly-efficient operating model. The system reportedly confirms transactions in three seconds and has the capacity to process over 100,000 transactions per second. According to the team, the currency has a fixed supply of coins that has been distributed during the past two years to over 150,000 accounts in over 180 countries. GREENPOWER envisions itself as a store-of-value unit at the center of an ecosystem of companies. GREENPOWER is intended to be the currency used as loyalty rewards by millions of merchants worldwide.\r\n\r\n- Facebook - https://www.facebook.com/GrnpowerOfficial/\r\n- Instagram - https://www.instagram.com/grnpower_official/","notice":null,"date_added":"2018-05-21T00:00:00.000Z","tags":null,"platform":null,"category":"coin"}