{"urls":{"website":["http://hyperpay.tech/"],"technical_doc":[],"twitter":["https://twitter.com/hyperpay_tech"],"reddit":[],"message_board":["https://weibo.com/u/6358820994?refer_flag=1005050010_&is_hot=1"],"announcement":[],"chat":[],"explorer":["https://explorer.qtum.org/token/f2703e93f87b846a7aacec1247beaec1c583daa4"],"source_code":[]},"logo":"https://s2.coinmarketcap.com/static/img/coins/64x64/2329.png","id":2329,"name":"Hyper Pay","symbol":"HPY","slug":"hyper-pay","description":"Hyper Pay (HPY) is a cryptocurrency token and operates on the Qtum platform. Hyper Pay has a current supply of 2,650,000,000 with ? in circulation. The last known price of Hyper Pay is $0.000808 USD and is down -1.51% over the last 24 hours. It is currently trading on 2 active market(s) with $2,424.00 traded over the last 24 hours. More information can be found at http://hyperpay.tech/.","notice":null,"date_added":"2017-12-31T00:00:00.000Z","tags":null,"platform":{"id":1684,"name":"Qtum","symbol":"QTUM","slug":"qtum","token_address":"f2703e93f87b846a7aacec1247beaec1c583daa4"},"category":"token"}