{"urls":{"website":["https://www.jobchain.com/"],"technical_doc":["https://www.jobchain.com/Whitepaper.pdf"],"twitter":["https://twitter.com/jobchain"],"reddit":[],"message_board":["https://medium.com/jobchain"],"announcement":[],"chat":["http://t.me/JobchainOfficial","https://discord.gg/jb6rFgE"],"explorer":["https://etherscan.io/token/0x17280DA053596E097604839C61A2eF5efb7d493f","https://ethplorer.io/address/0x17280DA053596E097604839C61A2eF5efb7d493f"],"source_code":[]},"logo":"https://s2.coinmarketcap.com/static/img/coins/64x64/4287.png","id":4287,"name":"Jobchain","symbol":"JOB","slug":"jobchain","description":"Jobchain is an ecosystem that aims to enable anybody to find jobs or hire personnel using cryptocurrency.","notice":null,"date_added":"2019-12-23T00:00:00.000Z","tags":null,"platform":{"id":1027,"name":"Ethereum","symbol":"ETH","slug":"ethereum","token_address":"0x17280DA053596E097604839C61A2eF5efb7d493f"},"category":"token"}