{"urls":{"website":["http://lbtc.io/"],"technical_doc":["http://lbtc.io/web/viewer.html"],"twitter":["https://twitter.com/LightningBTC"],"reddit":[],"message_board":["https://medium.com/lightning-bitcoin-blog"],"announcement":[],"chat":["https://twitter.com/LightningBTC","https://t.me/LightningBTC"],"explorer":["http://explorer.lbtc.io","https://lbtcscan.io/"],"source_code":["https://github.com/lbtcio"]},"logo":"https://s2.coinmarketcap.com/static/img/coins/64x64/2335.png","id":2335,"name":"Lightning Bitcoin","symbol":"LBTC","slug":"lightning-bitcoin","description":"Lightning Bitcoin (LBTC) is a cryptocurrency. Users are able to generate LBTC through the process of mining. Lightning Bitcoin has a current supply of 7,465,926 with 3,860,807.622 in circulation. The last known price of Lightning Bitcoin is $2.01 USD and is down -1.53% over the last 24 hours. It is currently trading on 16 active market(s) with $2,275,764.559 traded over the last 24 hours. More information can be found at http://lbtc.io/.","notice":null,"date_added":"2018-01-03T00:00:00.000Z","tags":["mineable"],"platform":null,"category":"coin"}