{"urls":{"website":["https://www.medibit.org/"],"technical_doc":["https://docs.wixstatic.com/ugd/381b09_e54eae0413b7427b90e61608e5f84d4e.pdf"],"twitter":["https://twitter.com/OfficialMedibit"],"reddit":[],"message_board":[],"announcement":[],"chat":["https://t.me/MediBit_EN","https://t.me/medibit_notic"],"explorer":["https://etherscan.io/token/0x737fa0372c8d001904ae6acaf0552d4015f9c947","https://ethplorer.io/address/0x737fa0372c8d001904ae6acaf0552d4015f9c947"],"source_code":[]},"logo":"https://s2.coinmarketcap.com/static/img/coins/64x64/3582.png","id":3582,"name":"MediBit","symbol":"MEDIBIT","slug":"medibit","description":"MediBit (MEDIBIT) is a cryptocurrency token and operates on the Ethereum platform. MediBit has a current supply of 50,000,000,000 with ? in circulation. The last known price of MediBit is $0.000003 USD and is down -1.34% over the last 24 hours. It is currently trading on 2 active market(s) with $27,929.18 traded over the last 24 hours. More information can be found at https://www.medibit.org/.","notice":null,"date_added":"2018-11-01T00:00:00.000Z","tags":null,"platform":{"id":1027,"name":"Ethereum","symbol":"ETH","slug":"ethereum","token_address":"0x737fa0372c8d001904ae6acaf0552d4015f9c947"},"category":"token"}