{"urls":{"website":["https://micromines.co/"],"technical_doc":["https://micromines.co/wp-content/uploads/2018/10/wp-fix-mcr.pdf"],"twitter":["https://twitter.com/Microminestoken"],"reddit":[],"message_board":["https://medium.com/@micromines"],"announcement":["https://bitcointalk.org/index.php?topic=5057361"],"chat":["https://t.me/MicroMines"],"explorer":["https://etherscan.io/token/0xbe6c8f2810ef39420d2dc2901b8414c8c45fee6d","https://ethplorer.io/address/0xbe6c8f2810ef39420d2dc2901b8414c8c45fee6d"],"source_code":["https://github.com/micromines/"]},"logo":"https://s2.coinmarketcap.com/static/img/coins/64x64/3610.png","id":3610,"name":"Micromines","symbol":"MICRO","slug":"micromines","description":"Micromines (MICRO) is a cryptocurrency token and operates on the Ethereum platform. Micromines has a current supply of 18,000,000,000 with 17,999,261,363.694 in circulation. The last known price of Micromines is $0.000002 USD and is down -9.69% over the last 24 hours. It is currently trading on 4 active market(s) with $22.53 traded over the last 24 hours. More information can be found at https://micromines.co/.","notice":null,"date_added":"2018-11-19T00:00:00.000Z","tags":null,"platform":{"id":1027,"name":"Ethereum","symbol":"ETH","slug":"ethereum","token_address":"0xbe6c8f2810ef39420d2dc2901b8414c8c45fee6d"},"category":"token"}