{"urls":{"website":["https://muzika.network"],"technical_doc":["https://muzika.network/assets/mzk-whitepaper-en.pdf"],"twitter":["https://twitter.com/muzika_official"],"reddit":["https://reddit.com/r/muzikaofficial"],"message_board":["https://medium.com/muzika-official"],"announcement":[],"chat":["https://t.me/muzika_english","https://t.me/muzika_korean"],"explorer":["https://etherscan.io/token/0x1f35a281036be57e64e7e7a2a556b4f888a1b829","https://ethplorer.io/address/0x1f35a281036be57e64e7e7a2a556b4f888a1b829"],"source_code":["https://github.com/MuzikaFoundation"]},"logo":"https://s2.coinmarketcap.com/static/img/coins/64x64/3938.png","id":3938,"name":"Muzika","symbol":"MZK","slug":"muzika","description":"Created by Mapiacompany, Muzika aims to become the token economy for music by closing the gap between fans and artist, creating a new ecosystem where fans and artists can be rewarded for their value creation, and leveraging blockchain technology to address long-standing issues in the digital music industry.","notice":null,"date_added":"2019-05-15T00:00:00.000Z","tags":null,"platform":{"id":1027,"name":"Ethereum","symbol":"ETH","slug":"ethereum","token_address":"0x1f35a281036be57e64e7e7a2a556b4f888a1b829"},"category":"token"}