{"urls":{"website":["https://naviaddress.com/"],"technical_doc":[],"twitter":["https://twitter.com/naviaddress"],"reddit":["https://reddit.com/r/Naviaddress"],"message_board":[],"announcement":[],"chat":["https://t.me/naviaddressnews"],"explorer":["https://etherscan.io/token/0x588047365df5ba589f923604aac23d673555c623","https://ethplorer.io/address/0x588047365df5ba589f923604aac23d673555c623"],"source_code":["https://github.com/naviworld/navi-token/"]},"logo":"https://s2.coinmarketcap.com/static/img/coins/64x64/2825.png","id":2825,"name":"Naviaddress","symbol":"NAVI","slug":"naviaddress","description":"Naviaddress (NAVI) is a cryptocurrency token and operates on the Ethereum platform. Naviaddress has a current supply of 1,000,000,000 with 242,550,845.354 in circulation. The last known price of Naviaddress is $0.000150 USD and is down -1.82% over the last 24 hours. It is currently trading on 2 active market(s) with $14.83 traded over the last 24 hours. More information can be found at https://naviaddress.com/.","notice":null,"date_added":"2018-05-28T00:00:00.000Z","tags":null,"platform":{"id":1027,"name":"Ethereum","symbol":"ETH","slug":"ethereum","token_address":"0x588047365df5ba589f923604aac23d673555c623"},"category":"token"}