{"urls":{"website":["http://nervos.org/"],"technical_doc":["https://github.com/nervosnetwork/rfcs/blob/master/rfcs/0002-ckb/0002-ckb.md"],"twitter":["https://twitter.com/nervosnetwork"],"reddit":["https://reddit.com/r/NervosNetwork"],"message_board":["https://medium.com/nervosnetwork","https://talk.nervos.org/"],"announcement":[],"chat":["https://t.me/nervosnetwork","https://talk.nervos.org/"],"explorer":["https://explorer.nervos.org/"],"source_code":["https://github.com/nervosnetwork"]},"logo":"https://s2.coinmarketcap.com/static/img/coins/64x64/4948.png","id":4948,"name":"Nervos Network","symbol":"CKB","slug":"nervos-network","description":"The Nervos Network describes itself as an open-source public blockchain ecosystem and collection of protocols. The Nervos CKB (Common Knowledge Base) is the layer 1, proof of work public blockchain protocol of the Nervos Network. It reportedly allows any crypto-asset to be stored with the security, immutability and permissionless nature of Bitcoin while enabling smart contracts and layer 2 scaling. It aims to capture the total network value through its \"store of value\" crypto-economic design and native token, the CKByte.","notice":null,"date_added":"2019-11-19T00:00:00.000Z","tags":null,"platform":null,"category":"coin"}