{"urls":{"website":["https://nexty.io/"],"technical_doc":["https://nexty.io/images/nexty-whitepaper.pdf"],"twitter":["https://twitter.com/nextyio"],"reddit":[],"message_board":["https://medium.com/nextyplatform"],"announcement":["https://bitcointalk.org/index.php?topic=2498919"],"chat":["https://t.me/nexty_io"],"explorer":["https://explorer.nexty.io/home"],"source_code":["https://github.com/nextyio"]},"logo":"https://s2.coinmarketcap.com/static/img/coins/64x64/2714.png","id":2714,"name":"Nexty","symbol":"NTY","slug":"nexty","description":"Nexty describes itself as a blockchain platform that specializes in payments and smart contracts. The team intends to implement the latest research on distributed systems to enable users to have full control of their finances. NewSD, the Nexty stablecoin, is intended to address market fluctuations and what it believes to be a lack of decentralization in stablecoins. Nexty aims to combine the convenience of a payment platform with security. Accroding to the team, Nexty provides security measures for assets moving on the network with DCCS and its proprietary consensus mechanism, Proof-Of-Foundation, along with verifiable delay function (VDF).","notice":null,"date_added":"2018-05-07T00:00:00.000Z","tags":["mineable"],"platform":null,"category":"coin"}