{"urls":{"website":["https://putincoin.org"],"technical_doc":["https://putincoin.org/putincoin.pdf"],"twitter":["https://twitter.com/PutinCoinPUT"],"reddit":["https://reddit.com/r/PutinCoin"],"message_board":["https://putincoin.org/forum/"],"announcement":["https://bitcointalk.org/index.php?topic=1847881"],"chat":["https://putincoin.org/chat.html"],"explorer":["https://chainz.cryptoid.info/put/"],"source_code":["https://github.com/PutinCoinPUT/PutinCoin"]},"logo":"https://s2.coinmarketcap.com/static/img/coins/64x64/1299.png","id":1299,"name":"PutinCoin","symbol":"PUT","slug":"putincoin","description":"PutinCoin (PUT) is a cryptocurrency. Users are able to generate PUT through the process of mining. PutinCoin has a current supply of 972,892,308.509. The last known price of PutinCoin is $0.000173 USD and is down -1.00% over the last 24 hours. It is currently trading on 1 active market(s) with $4.78 traded over the last 24 hours. More information can be found at https://putincoin.org.","notice":null,"date_added":"2016-07-07T00:00:00.000Z","tags":["mineable"],"platform":null,"category":"coin"}