{"urls":{"website":["https://smartplay.tech/"],"technical_doc":["https://smartplay.tech/white-paper"],"twitter":["https://twitter.com/smartplaytech"],"reddit":["https://reddit.com/r/smartplaytech"],"message_board":[],"announcement":["https://bitcointalk.org/index.php?topic=1826686"],"chat":[],"explorer":["https://etherscan.io/token/0xcced5b8288086be8c38e23567e684c3740be4d48"],"source_code":["https://github.com/Smartroulette"]},"logo":"https://s2.coinmarketcap.com/static/img/coins/64x64/1683.png","id":1683,"name":"RouletteToken","symbol":"RLT","slug":"roulettetoken","description":"RouletteToken (RLT) is a cryptocurrency token and operates on the Ethereum platform. RouletteToken has a current supply of 11,344,952.514 with 11,344,229.514 in circulation. The last known price of RouletteToken is $0.000693 USD and is down -11.99% over the last 24 hours. It is currently trading on 1 active market(s) with $125.27 traded over the last 24 hours. More information can be found at https://smartplay.tech/.","notice":null,"date_added":"2017-05-22T00:00:00.000Z","tags":null,"platform":{"id":1027,"name":"Ethereum","symbol":"ETH","slug":"ethereum","token_address":"0xcced5b8288086be8c38e23567e684c3740be4d48"},"category":"token"}