{"urls":{"website":["https://ico.savedroid.com/"],"technical_doc":[],"twitter":["https://twitter.com/savedroidHQ"],"reddit":["https://reddit.com/r/savedroid_ico"],"message_board":["https://medium.com/@ico_8796"],"announcement":["https://bitcointalk.org/index.php?topic=2578161"],"chat":["https://t.me/savedroid"],"explorer":["https://etherscan.io/token/0xbdeb4b83251fb146687fa19d1c660f99411eefe3","https://ethplorer.io/address/0xbdeb4b83251fb146687fa19d1c660f99411eefe3"],"source_code":[]},"logo":"https://s2.coinmarketcap.com/static/img/coins/64x64/3161.png","id":3161,"name":"savedroid","symbol":"SVD","slug":"savedroid","description":"savedroid (SVD) is a cryptocurrency token and operates on the Ethereum platform. savedroid has a current supply of 6,997,578,543 with 2,688,339,237.972 in circulation. The last known price of savedroid is $0.000122 USD and is down -1.54% over the last 24 hours. It is currently trading on 5 active market(s) with $11.11 traded over the last 24 hours. More information can be found at https://ico.savedroid.com/.","notice":null,"date_added":"2018-08-13T00:00:00.000Z","tags":null,"platform":{"id":1027,"name":"Ethereum","symbol":"ETH","slug":"ethereum","token_address":"0xbdeb4b83251fb146687fa19d1c660f99411eefe3"},"category":"token"}