{"urls":{"website":["https://tokensale.snov.io/"],"technical_doc":["https://tokensale.snov.io/docs/WhitePaperEn.pdf"],"twitter":["https://twitter.com/snovio_ico"],"reddit":["https://reddit.com/r/snovio_ico"],"message_board":["https://medium.com/@ico_snovio"],"announcement":["https://bitcointalk.org/index.php?topic=2111272.0"],"chat":["https://t.me/snovio_ico"],"explorer":["https://etherscan.io/token/0xbdc5bac39dbe132b1e030e898ae3830017d7d969","https://ethplorer.io/address/0xbdc5bac39dbe132b1e030e898ae3830017d7d969"],"source_code":[]},"logo":"https://s2.coinmarketcap.com/static/img/coins/64x64/2258.png","id":2258,"name":"Snovian.Space","symbol":"SNOV","slug":"snov","description":"Snovian.Space (SNOV) is a cryptocurrency token and operates on the Ethereum platform. Snovian.Space has a current supply of 388,233,659 with 284,283,172 in circulation. The last known price of Snovian.Space is $0.001286 USD and is down -54.82% over the last 24 hours. It is currently trading on 1 active market(s) with $285.68 traded over the last 24 hours. More information can be found at https://tokensale.snov.io/.","notice":null,"date_added":"2017-12-08T00:00:00.000Z","tags":null,"platform":{"id":1027,"name":"Ethereum","symbol":"ETH","slug":"ethereum","token_address":"0xbdc5bac39dbe132b1e030e898ae3830017d7d969"},"category":"token"}