{"urls":{"website":["https://stipend.me/"],"technical_doc":["https://stipend.me//wp-content/uploads/2018/02/Stipend-Light%20-%20Whitepaper.pdf"],"twitter":["https://twitter.com/StipendOff"],"reddit":["https://reddit.com/r/stipend"],"message_board":[],"announcement":["https://bitcointalk.org/index.php?topic=4694590"],"chat":["https://t.me/StipendOfficial","https://discordapp.com/invite/Q6vyckx"],"explorer":["http://explorer.stipend.me/","http://spd.overemo.com/"],"source_code":["https://github.com/Stipend-Developer/stipend"]},"logo":"https://s2.coinmarketcap.com/static/img/coins/64x64/2616.png","id":2616,"name":"Stipend","symbol":"SPD","slug":"stipend","description":"The Stipend Project aims to develop the next generation of freelancing ecosystem that leverages the unique & powerful features of blockchain technology towards a 0% Commission Freelance Platform. Stipend is building an environment with multiple technology levels that it hopes will benefit prospective employers, freelancers, and intermediaries tremendously.","notice":null,"date_added":"2018-03-27T00:00:00.000Z","tags":["mineable"],"platform":null,"category":"coin"}