{"urls":{"website":["https://themis.network/"],"technical_doc":[],"twitter":["https://twitter.com/themisnetwork"],"reddit":[],"message_board":[],"announcement":[],"chat":["https://t.me/themisnetworkofficial"],"explorer":["https://etherscan.io/token/0x60c68a87be1e8a84144b543aacfa77199cd3d024","https://etherscan.io/address/0x60c68a87be1e8a84144b543aacfa77199cd3d024","https://themiscan.io/explorer"],"source_code":["https://github.com/themis-network/go-themis"]},"logo":"https://s2.coinmarketcap.com/static/img/coins/64x64/3127.png","id":3127,"name":"Themis","symbol":"GET","slug":"themis","description":"Themis provides escrow services for decentralized digital currencies.","notice":null,"date_added":"2018-08-09T00:00:00.000Z","tags":null,"platform":{"id":1027,"name":"Ethereum","symbol":"ETH","slug":"ethereum","token_address":"0x60c68a87be1e8a84144b543aacfa77199cd3d024"},"category":"token"}