{"urls":{"website":["http://tratin.io/"],"technical_doc":["http://tratin.io/whitepaper/"],"twitter":["https://twitter.com/tratintoken"],"reddit":[],"message_board":[],"announcement":["https://bitcointalk.org/index.php?topic=4943791.0"],"chat":["https://t.me/tratin"],"explorer":["https://etherscan.io/token/0x3eb55d5b22ee0f9b03d59b4994c5ae7fe811be92","https://ethplorer.io/address/0x3eb55d5b22ee0f9b03d59b4994c5ae7fe811be92"],"source_code":["https://github.com/tratinproject/Tratin"]},"logo":"https://s2.coinmarketcap.com/static/img/coins/64x64/4005.png","id":4005,"name":"Tratin","symbol":"TRAT","slug":"tratin","description":"Tratin describes itself as an open source peer-to-peer and business-to-customer cryptocurrency that aims to offer secure, instant, and private transactions with unit value fungibility and escrow function.","notice":null,"date_added":"2019-06-11T00:00:00.000Z","tags":null,"platform":{"id":1027,"name":"Ethereum","symbol":"ETH","slug":"ethereum","token_address":"0x3eb55d5b22ee0f9b03d59b4994c5ae7fe811be92"},"category":"token"}