{"urls":{"website":["http://trollcoin.com"],"technical_doc":["https://trollcoin.com/specifications"],"twitter":["https://twitter.com/trollcoinbase"],"reddit":[],"message_board":[],"announcement":["https://bitcointalk.org/index.php?topic=452810.0"],"chat":[],"explorer":["https://chainz.cryptoid.info/troll/"],"source_code":["https://github.com/TrollCoin2/"]},"logo":"https://s2.coinmarketcap.com/static/img/coins/64x64/638.png","id":638,"name":"Trollcoin","symbol":"TROLL","slug":"trollcoin","description":"Launched as a parody currency on 14 March 2014 by an anonymous developer, Trollcoin has grown into a Twitch & Twitter targeted tipping service via its [centrally managed platform](https://bot.trollcoin.com) while serving as a real-time experiment in negative brand marketing - how a cryptocurrency branded in trolling can proliferate.\r\n\r\nTrollcoin's Proof of Work (Scrypt) & Proof of Stake hybrid blockchain is managed by Karl Wickman based in Los Angeles who took control of the project in May 2014 and is supported by a primarily anonymous community of volunteers around the globe. Trollcoinbot services platform is developed and managed by Colt Fortenberry.","notice":null,"date_added":"2014-09-30T00:00:00.000Z","tags":["mineable"],"platform":null,"category":"coin"}