{"urls":{"website":["https://unibright.io/"],"technical_doc":["https://unibright.io/download/unibright_whitepaper.pdf"],"twitter":["https://twitter.com/Unibrightio"],"reddit":["https://reddit.com/r/Unibright"],"message_board":["https://medium.com/@UnibrightIO"],"announcement":["https://bitcointalk.org/index.php?topic=2892915"],"chat":["https://t.me/unibright_io"],"explorer":["https://etherscan.io/token/0x8400d94a5cb0fa0d041a3788e395285d61c9ee5e","https://ethplorer.io/address/0x8400d94a5cb0fa0d041a3788e395285d61c9ee5e"],"source_code":[]},"logo":"https://s2.coinmarketcap.com/static/img/coins/64x64/2758.png","id":2758,"name":"Unibright","symbol":"UBT","slug":"unibright","description":"Unibright (UBT) is a cryptocurrency token and operates on the Ethereum platform. Unibright has a current supply of 150,000,000 with 148,579,219.243 in circulation. The last known price of Unibright is $0.022215 USD and is down -3.55% over the last 24 hours. It is currently trading on 7 active market(s) with $78,901.56 traded over the last 24 hours. More information can be found at https://unibright.io/.","notice":null,"date_added":"2018-05-21T00:00:00.000Z","tags":null,"platform":{"id":1027,"name":"Ethereum","symbol":"ETH","slug":"ethereum","token_address":"0x8400d94a5cb0fa0d041a3788e395285d61c9ee5e"},"category":"token"}