{"urls":{"website":["https://www.virtacoin.world/"],"technical_doc":[],"twitter":[],"reddit":["https://reddit.com/r/virtacoin"],"message_board":[],"announcement":["https://bitcointalk.org/index.php?topic=1462517.0"],"chat":[],"explorer":["https://chainz.cryptoid.info/vta/","https://www.virtacoin.world/C-Data/"],"source_code":["https://github.com/virtacoin/VirtaCoinProject"]},"logo":"https://s2.coinmarketcap.com/static/img/coins/64x64/520.png","id":520,"name":"Virtacoin","symbol":"VTA","slug":"virtacoin","description":"Virtacoin (VTA) is a cryptocurrency. Users are able to generate VTA through the process of mining. Virtacoin has a current supply of 12,666,916,683.2 with 5,201,310,113.21 in circulation. The last known price of Virtacoin is $3.82e-7 USD and is down -15.77% over the last 24 hours. It is currently trading on 1 active market(s) with $5.25 traded over the last 24 hours. More information can be found at https://www.virtacoin.world/.","notice":null,"date_added":"2014-08-09T00:00:00.000Z","tags":["mineable"],"platform":null,"category":"coin"}